nameko_design/__init__.py
nameko_design/main.py
nameko_design/sample.py
nameko_design-0.1.dev2.dist-info/entry_points.txt
nameko_design-0.1.dev2.dist-info/LICENSE
nameko_design-0.1.dev2.dist-info/WHEEL
nameko_design-0.1.dev2.dist-info/METADATA
nameko_design-0.1.dev2.dist-info/RECORD
