Metadata-Version: 2.1
Name: nameko-design
Version: 0.1.dev2
Summary: Generate http files from design schema inspired by goa
Home-page: https://github.com/yukinagae/nameko-design
License: MIT
Keywords: nameko,microservices,design,framework
Author: yukinagae
Author-email: yuki.nagae1130@gmail.com
Requires-Python: >=3.6,<4.0
Classifier: License :: OSI Approved :: MIT License
Classifier: Programming Language :: Python :: 3
Classifier: Programming Language :: Python :: 3.6
Classifier: Programming Language :: Python :: 3.7
Requires-Dist: Jinja2 (>=2.10,<3.0)
Project-URL: Repository, https://github.com/yukinagae/nameko-design
